CHANGELOG
COPYING
MANIFEST.in
README
setup.py
swsg/__init__.py
swsg/cli.py
swsg/file_paths.py
swsg/loggers.py
swsg/projects.py
swsg/sources.py
swsg/template_functions.py
swsg/templates.py
swsg/utils.py
swsg.egg-info/PKG-INFO
swsg.egg-info/SOURCES.txt
swsg.egg-info/dependency_links.txt
swsg.egg-info/entry_points.txt
swsg.egg-info/requires.txt
swsg.egg-info/top_level.txt
tests/test_cli.py
tests/test_logging.py
tests/test_projects.py
tests/test_sources.py
tests/test_templates.py
tests/utils.py