Metadata-Version: 1.0
Name: swsg
Version: 0.3.0
Summary: SWSG (Static Web Site Generator) is a tool to generate static web pages.
Home-page: http://github.com/derdon/swsg
Author: Simon Liedtke
Author-email: liedtke.simon@googlemail.com
License: WTFPL
Platform: UNKNOWN
Classifier: Development Status :: 4 - Beta
Classifier: Environment :: Console
Classifier: Intended Audience :: Developers
Classifier: Operating System :: MacOS :: MacOS X
Classifier: Operating System :: POSIX
Classifier: Operating System :: Unix
Classifier: Topic :: Internet :: WWW/HTTP :: Dynamic Content
Classifier: Topic :: Text Processing
Classifier: Topic :: Text Processing :: Markup
